pytest_himark/__init__.py
pytest_himark/plugin.py
pytest_himark-0.2.3.dist-info/LICENSE
pytest_himark-0.2.3.dist-info/METADATA
pytest_himark-0.2.3.dist-info/WHEEL
pytest_himark-0.2.3.dist-info/entry_points.txt
pytest_himark-0.2.3.dist-info/top_level.txt
pytest_himark-0.2.3.dist-info/RECORD
