Metadata-Version: 2.1
Name: pytest-himark
Version: 0.2.3
Summary: This plugin aims to create markers automatically based on a json configuration.
Author-email: Rodolphe Mete Soyding <r.soyding@gmail.com>
Maintainer-email: Rodolphe Mete Soyding <r.soyding@gmail.com>
License: 
Project-URL: Repository, https://github.com/supermete/pytest-himark
Classifier: Framework :: Pytest
Classifier: Development Status :: 4 - Beta
Classifier: Intended Audience :: Developers
Classifier: Topic :: Software Development :: Testing
Classifier: Operating System :: OS Independent
Classifier: Programming Language :: Python
Classifier: Programming Language :: Python :: 3.8
Classifier: Programming Language :: Python :: 3.9
Classifier: Programming Language :: Python :: 3.10
Classifier: Programming Language :: Python :: 3.11
Classifier: Programming Language :: Python :: 3.12
Classifier: Programming Language :: Python :: 3 :: Only
Classifier: Programming Language :: Python :: Implementation :: CPython
Classifier: Programming Language :: Python :: Implementation :: PyPy
Classifier: License :: OSI Approved :: MIT License
Requires-Python: >=3.8
License-File: LICENSE
Requires-Dist: pytest >=6.2.0
